cosecurity_utility_internal_lib/__init__.py
cosecurity_utility_internal_lib/aws.py
cosecurity_utility_internal_lib/image.py
cosecurity_utility_internal_lib/logger.py
cosecurity_utility_internal_lib-0.0.24.dist-info/LICENSE
cosecurity_utility_internal_lib-0.0.24.dist-info/METADATA
cosecurity_utility_internal_lib-0.0.24.dist-info/WHEEL
cosecurity_utility_internal_lib-0.0.24.dist-info/top_level.txt
cosecurity_utility_internal_lib-0.0.24.dist-info/RECORD
