Metadata-Version: 2.1
Name: cosecurity-utility-internal-lib
Version: 0.0.24
Summary: Built-in utility library for application development by the CoSecurity infrastructure
Classifier: Programming Language :: Python :: 3
Classifier: License :: OSI Approved :: MIT License
Classifier: Operating System :: OS Independent
Requires-Python: >=3.6
License-File: LICENSE
Requires-Dist: psycopg2 (==2.9.3)
Requires-Dist: boto3 (==1.21.36)
